adafruit_circuitpython_esp_atcontrol-0.11.5.dist-info/licenses/LICENSE
adafruit_espatcontrol/__init__.py
adafruit_espatcontrol/adafruit_espatcontrol.py
adafruit_espatcontrol/adafruit_espatcontrol_socket.py
adafruit_espatcontrol/adafruit_espatcontrol_wifimanager.py
adafruit_circuitpython_esp_atcontrol-0.11.5.dist-info/METADATA
adafruit_circuitpython_esp_atcontrol-0.11.5.dist-info/WHEEL
adafruit_circuitpython_esp_atcontrol-0.11.5.dist-info/top_level.txt
adafruit_circuitpython_esp_atcontrol-0.11.5.dist-info/RECORD
