Metadata-Version: 2.4
Name: adafruit-circuitpython-esp-atcontrol
Version: 0.11.5
Summary: CircuitPython driver for communicating using ESP AT command set.
Author-email: Adafruit Industries <circuitpython@adafruit.com>
License: MIT
Project-URL: Homepage, https://github.com/adafruit/Adafruit_CircuitPython_ESP_ATcontrol
Keywords: adafruit,software,esp,at,atcontrol,internet,communication,micropython,circuitpython
Classifier: Intended Audience :: Developers
Classifier: Topic :: Software Development :: Libraries
Classifier: Topic :: Software Development :: Embedded Systems
Classifier: Topic :: System :: Hardware
Classifier: License :: OSI Approved :: MIT License
Classifier: Programming Language :: Python :: 3
License-File: LICENSE
Requires-Dist: Adafruit-Blinka
Requires-Dist: adafruit-circuitpython-typing>=1.4.0
Requires-Dist: adafruit-circuitpython-connectionmanager
Requires-Dist: adafruit-circuitpython-requests
Requires-Dist: pyserial
Provides-Extra: optional
Dynamic: license-file
